fmtr/tools/__init__.py
fmtr/tools/api_tools.py
fmtr/tools/async_tools.py
fmtr/tools/augmentation_tools.py
fmtr/tools/av_tools.py
fmtr/tools/caching_tools.py
fmtr/tools/constants.py
fmtr/tools/context_tools.py
fmtr/tools/data_modelling_tools.py
fmtr/tools/dataclass_tools.py
fmtr/tools/datatype_tools.py
fmtr/tools/datetime_tools.py
fmtr/tools/debugging_tools.py
fmtr/tools/environment_tools.py
fmtr/tools/function_tools.py
fmtr/tools/google_api_tools.py
fmtr/tools/hash_tools.py
fmtr/tools/hfh_tools.py
fmtr/tools/html_tools.py
fmtr/tools/http_tools.py
fmtr/tools/import_tools.py
fmtr/tools/inherit_tools.py
fmtr/tools/inspection_tools.py
fmtr/tools/iterator_tools.py
fmtr/tools/json_fix_tools.py
fmtr/tools/json_tools.py
fmtr/tools/logging_tools.py
fmtr/tools/merging_tools.py
fmtr/tools/metric_tools.py
fmtr/tools/mqtt_tools.py
fmtr/tools/name_tools.py
fmtr/tools/netrc_tools.py
fmtr/tools/networking_tools.py
fmtr/tools/openai_tools.py
fmtr/tools/packaging_tools.py
fmtr/tools/parallel_tools.py
fmtr/tools/pattern_tools.py
fmtr/tools/pdf_tools.py
fmtr/tools/platform_tools.py
fmtr/tools/process_tools.py
fmtr/tools/profiling_tools.py
fmtr/tools/random_tools.py
fmtr/tools/semantic_tools.py
fmtr/tools/settings_tools.py
fmtr/tools/spaces_tools.py
fmtr/tools/string_tools.py
fmtr/tools/tabular_tools.py
fmtr/tools/tokenization_tools.py
fmtr/tools/tools.py
fmtr/tools/unicode_tools.py
fmtr/tools/version
fmtr/tools/webhook_tools.py
fmtr/tools/yaml_tools.py
fmtr/tools/youtube_tools.py
fmtr/tools/ai_tools/__init__.py
fmtr/tools/ai_tools/agentic_tools.py
fmtr/tools/ai_tools/inference_tools.py
fmtr/tools/database_tools/__init__.py
fmtr/tools/database_tools/document.py
fmtr/tools/dns_tools/__init__.py
fmtr/tools/dns_tools/client.py
fmtr/tools/dns_tools/dm.py
fmtr/tools/dns_tools/proxy.py
fmtr/tools/dns_tools/server.py
fmtr/tools/docker_tools/__init__.py
fmtr/tools/entrypoints/__init__.py
fmtr/tools/entrypoints/cache_hfh.py
fmtr/tools/entrypoints/ep_test.py
fmtr_tools-1.4.74.dist-info/licenses/LICENSE
fmtr_tools-1.4.74.dist-info/METADATA
fmtr_tools-1.4.74.dist-info/WHEEL
fmtr_tools-1.4.74.dist-info/entry_points.txt
fmtr_tools-1.4.74.dist-info/top_level.txt
fmtr_tools-1.4.74.dist-info/RECORD
